fiji_arnheim/__init__.py
fiji_arnheim/helper.py
fiji_arnheim/macros/__init__.py
fiji_arnheim/macros/base.py
fiji_arnheim/macros/filter.py
fiji_arnheim/macros/image_acting.py
fiji_arnheim/registries/__init__.py
fiji_arnheim/registries/helper.py
fiji_arnheim/run.py
fiji_arnheim-0.1.3.dist-info/entry_points.txt
fiji_arnheim-0.1.3.dist-info/WHEEL
fiji_arnheim-0.1.3.dist-info/METADATA
fiji_arnheim-0.1.3.dist-info/RECORD
