Metadata-Version: 2.1
Name: fiji-arnheim
Version: 0.1.3
Summary: Fiji with Arnheim Client Integrated
Home-page: https://github.com/jhnnsrs/fiji-arnheim
Author: jhnnsrs
Author-email: jhnnsrs@gmail.com
Requires-Python: >=3.8,<4.0
Classifier: Programming Language :: Python :: 3
Classifier: Programming Language :: Python :: 3.8
Classifier: Programming Language :: Python :: 3.9
Requires-Dist: bergen (>=0.3.31,<0.4.0)
Requires-Dist: grunnlag (>=0.2.9,<0.3.0)
Requires-Dist: pyimagej (>=1.0.0,<2.0.0)
